tpsimilarity/__init__.py
tpsimilarity/similarity.py
tpsimilarity-0.6.1.dist-info/LICENSE
tpsimilarity-0.6.1.dist-info/METADATA
tpsimilarity-0.6.1.dist-info/WHEEL
tpsimilarity-0.6.1.dist-info/top_level.txt
tpsimilarity-0.6.1.dist-info/RECORD
