Metadata-Version: 2.2
Name: tpsimilarity
Version: 0.6.1
Summary: Package to compute TP similarities between nodes in a network.
Author: Sadamori Kojaku, Attila Varga
Author-email: "Filipi N. Silva" <filsilva@iu.edu>
License: MIT License
Classifier: Programming Language :: Python :: 3
Classifier: License :: OSI Approved :: MIT License
Classifier: Operating System :: OS Independent
Requires-Python: >=3.0
License-File: LICENSE
Requires-Dist: numpy
Requires-Dist: tqdm
Requires-Dist: pandas
Requires-Dist: python-igraph
Requires-Dist: cxrandomwalk
Requires-Dist: networkx
Requires-Dist: fastnode2vec
Requires-Dist: toml
